ionpy/Buffer.py
ionpy/Builder.py
ionpy/BuilderCompileOption.py
ionpy/Graph.py
ionpy/Node.py
ionpy/Param.py
ionpy/Port.py
ionpy/Type.py
ionpy/TypeCode.py
ionpy/__init__.py
ionpy/native.py
ionpy/version.py
ionpy/module/macos/README.md
ionpy/module/macos/libHalide.17.dylib
ionpy/module/macos/libaravis-0.8.dylib
ionpy/module/macos/libion-bb.dylib
ionpy/module/macos/libion-core.dylib
ion_contrib_python-3.2.7.dist-info/LICENSE
ion_contrib_python-3.2.7.dist-info/LICENSE-3RD-PARTY
ion_contrib_python-3.2.7.dist-info/METADATA
ion_contrib_python-3.2.7.dist-info/WHEEL
ion_contrib_python-3.2.7.dist-info/top_level.txt
ion_contrib_python-3.2.7.dist-info/RECORD
