Metadata-Version: 2.2
Name: ion-contrib-python
Version: 3.2.7
Summary: Python Binding for ion-kit
Home-page: https://github.com/fixstars/ion-kit
Author: Takuro Iizuka
Author-email: t_iizuka@fixstars.com
License: MIT License
Classifier: Development Status :: 3 - Alpha
Classifier: Programming Language :: Python :: 3
Classifier: Programming Language :: Python :: 3 :: Only
Classifier: Programming Language :: Python :: 3.8
Classifier: Programming Language :: Python :: 3.9
Classifier: Programming Language :: Python :: 3.10
Classifier: Programming Language :: Python :: 3.11
Classifier: Programming Language :: Python :: 3.12
Classifier: License :: OSI Approved :: MIT License
Requires-Python: >=3.8.0
License-File: LICENSE
License-File: LICENSE-3RD-PARTY
Requires-Dist: numpy>=1.24
Dynamic: author
Dynamic: author-email
Dynamic: classifier
Dynamic: description
Dynamic: description-content-type
Dynamic: home-page
Dynamic: license
Dynamic: requires-dist
Dynamic: requires-python
Dynamic: summary
